LICENSE
README.md
setup.cfg
setup.py
jcopdl/__init__.py
jcopdl/callback.py
jcopdl/eval.py
jcopdl/exception.py
jcopdl/io.py
jcopdl/metrics.py
jcopdl/visualization.py
jcopdl.egg-info/PKG-INFO
jcopdl.egg-info/SOURCES.txt
jcopdl.egg-info/dependency_links.txt
jcopdl.egg-info/requires.txt
jcopdl.egg-info/top_level.txt
jcopdl/layers/__init__.py
jcopdl/layers/base.py
jcopdl/layers/block.py
jcopdl/layers/unet.py
jcopdl/layers/vgg.py
jcopdl/optim/__init__.py
jcopdl/optim/_lookahead.py
jcopdl/optim/_optimizer.py
jcopdl/optim/_radam.py
jcopdl/optim/_ralamb.py
jcopdl/snippets/__init__.py
jcopdl/snippets/const.py
jcopdl/snippets/widget.py
jcopdl/transforms/__init__.py
jcopdl/transforms/augment.py
jcopdl/transforms/sequence.py
jcopdl/utils/__init__.py
jcopdl/utils/conv_calculator.py
jcopdl/utils/decoding.py
jcopdl/utils/helper.py
jcopdl/utils/logits_sampling.py
jcopdl/utils/model_selection.py
jcopdl/utils/nb_check.py
jcopdl/utils/params_calculator.py
jcopdl/utils/random_state.py
jcopdl/utils/sampler.py
jcopdl/utils/dataloader/__init__.py
jcopdl/utils/dataloader/char_rnn.py
jcopdl/utils/dataloader/coco_detection.py
jcopdl/utils/dataloader/multilabel.py
jcopdl/utils/dataloader/text_generation.py
jcopdl/utils/dataloader/time_series.py