Metadata-Version: 2.1
Name: jcopdl
Version: 2.3.3
Summary: J.COp DL is a deep Learning package to complement pytorch workflow
Home-page: https://github.com/WiraDKP/jcopdl
Author: Wira Dharma Kencana Putra
Author-email: wiradharma_kencanaputra@yahoo.com
Keywords: deep learning dl jcop indonesia
Classifier: Programming Language :: Python :: 3.6
Classifier: Programming Language :: Python :: 3.7
Classifier: Programming Language :: Python :: 3.8
Classifier: Programming Language :: Python :: 3.9
Classifier: Programming Language :: Python :: 3.10
Classifier: Programming Language :: Python :: 3.11
Classifier: Intended Audience :: Developers
Classifier: Intended Audience :: Education
Classifier: Intended Audience :: Information Technology
Classifier: Intended Audience :: Science/Research
Classifier: Topic :: Scientific/Engineering :: Artificial Intelligence
Classifier: Natural Language :: Indonesian
Classifier: Natural Language :: English
Requires-Python: >=3.6.7
License-File: LICENSE
Requires-Dist: torch
Requires-Dist: torchvision
Requires-Dist: numpy
Requires-Dist: scipy
Requires-Dist: pandas
Requires-Dist: matplotlib
Requires-Dist: pillow
Requires-Dist: scikit-learn
Requires-Dist: pyperclip
Requires-Dist: tqdm
